dynaodbc/__init__.py
dynaodbc/_dyna_odbc_const.py
dynaodbc/dyna_odbc_connector.py
dynaodbc/dyna_odbc_mapping.py
dynaodbc/odbc_connection.py
dynaodbc-1.0.0.4.dist-info/LICENSE
dynaodbc-1.0.0.4.dist-info/METADATA
dynaodbc-1.0.0.4.dist-info/WHEEL
dynaodbc-1.0.0.4.dist-info/top_level.txt
dynaodbc-1.0.0.4.dist-info/RECORD
