Metadata-Version: 2.1
Name: dynaodbc
Version: 1.0.0.4
Summary: Python ODBC connector for the Dynizer
Home-page: https://github.com/Dynactionize/Dyna-ODBC
Author: Dynactionize NV
Author-email: info-belgium@dynationize.com
License: UNKNOWN
Platform: UNKNOWN
Classifier: Programming Language :: Python :: 3
Classifier: License :: OSI Approved :: MIT License
Classifier: Operating System :: OS Independent
Requires-Dist: pyodbc
Requires-Dist: dynapython
